russound_rio/__init__.py
russound_rio/rio.py
russound_rio-1.0.0.dist-info/LICENSE
russound_rio-1.0.0.dist-info/METADATA
russound_rio-1.0.0.dist-info/WHEEL
russound_rio-1.0.0.dist-info/top_level.txt
russound_rio-1.0.0.dist-info/RECORD
