Metadata-Version: 2.1
Name: russound_rio
Version: 1.0.0
Summary: Asyncio client for Russound RIO devices
Home-page: https://github.com/chphilli/russound_rio
Author: Chris Phillips
License: MIT
License-File: LICENSE
